vsag-0.1.2.dist-info/METADATA
vsag-0.1.2.dist-info/WHEEL
vsag-0.1.2.dist-info/licenses/LICENSE
vsag.libs/libquadmath-776d53b6.so.0
vsag.libs/libgfortran-93980b03.so.5
vsag.libs/libgomp-24e2ab19.so.1
vsag.libs/libvsag-86453d30.so
vsag/__init__.py
vsag/vsag.cpython-310-x86_64-linux-gnu.so
vsag-0.1.2.dist-info/RECORD
