Metadata-Version: 2.3
Name: vsag
Version: 0.1.2
Classifier: Programming Language :: Rust
Classifier: Programming Language :: Python :: Implementation :: CPython
Classifier: Programming Language :: Python :: Implementation :: PyPy
Classifier: Operating System :: OS Independent
Classifier: Topic :: Software Development
Classifier: Intended Audience :: Developers
License-File: LICENSE
Summary: VSAG Python Binding
Keywords: vector,search,llm,knn,hnsw,diskann
Author-email: Jiacai Liu <dev@liujiacai.net>
License: Apache-2.0
Requires-Python: >=3.8
Project-URL: Documentation, https://github.com/jiacai2050/vsag-py
Project-URL: Homepage, https://github.com/jiacai2050/vsag-py
Project-URL: Repository, https://github.com/jiacai2050/vsag-py
